README.rst
setup.py
aiohttp_session_flash/__init__.py
aiohttp_session_flash.egg-info/PKG-INFO
aiohttp_session_flash.egg-info/SOURCES.txt
aiohttp_session_flash.egg-info/dependency_links.txt
aiohttp_session_flash.egg-info/requires.txt
aiohttp_session_flash.egg-info/top_level.txt