Metadata-Version: 1.0
Name: aiohttp-session-flash
Version: 0.0.1
Summary: UNKNOWN
Home-page: https://github.com/IlyaSemenov/aiohttp_session_flash
Author: Ilya Semenov
Author-email: ilya@semenov.co
License: BSD
Platform: UNKNOWN
